retire/__init__.py
retire/retire.py
retire/data/__init__.py
retire/data/data.py
retire/examples/__init__.py
retire/examples/dotplot_config.py
retire/examples/heatmap_config.py
retire/explore/__init__.py
retire/explore/explore.py
retire/explore/utils.py
retire/resources/clean_scaled_us_coalplant_dataset.csv
retire/resources/generator_level_dataset.csv
retire/resources/projected_us_coalplant_dataset.csv
retire/resources/raw_2020-2023_retired_coalplants.csv
retire/resources/us_coal_plants_dataset.csv
retire/resources/graph/graphedge_df.csv
retire/resources/graph/graphnode_df.csv
retire/resources/results/group_analysis.csv
retire/resources/results/metrics.csv
retire/resources/results/news.csv
retire/resources/results/plant_level_match_explanations.csv
retire/resources/results/retired.csv
retire_coal-0.1.1.dist-info/licenses/LICENSE.md
retire_coal-0.1.1.dist-info/METADATA
retire_coal-0.1.1.dist-info/WHEEL
retire_coal-0.1.1.dist-info/top_level.txt
retire_coal-0.1.1.dist-info/RECORD
