Metadata-Version: 2.4
Name: retire-coal
Version: 0.1.1
Summary: A data-driven approach to strategizing US coal plant retirement using network analysis and contextual vulnerabilities.
Author-email: Krv Labs <team@krv.ai>
License: BSD-3-Clause
Project-URL: Homepage, https://github.com/Krv-Analytics/retire/
Keywords: coal,energy,retirement,network-analysis,policy,visualization
Classifier: Development Status :: 4 - Beta
Classifier: Intended Audience :: Science/Research
Classifier: License :: OSI Approved :: BSD License
Classifier: Programming Language :: Python :: 3.10
Classifier: Programming Language :: Python :: 3.11
Classifier: Programming Language :: Python :: 3.12
Classifier: Programming Language :: Python :: 3.13
Classifier: Topic :: Scientific/Engineering :: Information Analysis
Classifier: Topic :: Scientific/Engineering :: Visualization
Requires-Python: >=3.10
License-File: LICENSE.md
Requires-Dist: ipykernel>=6.30.1
Requires-Dist: ipywidgets>=8.1.7
Requires-Dist: matplotlib>=3.5.0
Requires-Dist: nbformat>=5.10.4
Requires-Dist: networkx>=2.8
Requires-Dist: numpy>=1.21.0
Requires-Dist: pandas>=1.5.0
Requires-Dist: plotly>=5.0.0
Requires-Dist: scikit-learn>=1.1.0
Requires-Dist: seaborn>=0.11.0
Requires-Dist: thema>=0.1.3
Provides-Extra: dev
Requires-Dist: pytest>=7.0.0; extra == "dev"
Requires-Dist: pytest-cov>=4.0.0; extra == "dev"
Requires-Dist: black>=22.0.0; extra == "dev"
Requires-Dist: flake8>=5.0.0; extra == "dev"
Requires-Dist: mypy>=1.0.0; extra == "dev"
Requires-Dist: tqdm>=4.67.1; extra == "dev"
Provides-Extra: docs
Requires-Dist: sphinx>=5.0.0; extra == "docs"
Requires-Dist: furo>=2022.6.21; extra == "docs"
Requires-Dist: myst-parser>=0.18.0; extra == "docs"
Requires-Dist: sphinx-autodoc-typehints>=1.19.0; extra == "docs"
Requires-Dist: sphinx-autobuild>=2021.3.14; extra == "docs"
Requires-Dist: sphinx-plotly-directive>=0.1.3; extra == "docs"
Requires-Dist: jupyter-sphinx>=0.4.0; extra == "docs"
Provides-Extra: notebooks
Requires-Dist: jupyter>=1.0.0; extra == "notebooks"
Requires-Dist: ipykernel>=6.0.0; extra == "notebooks"
Requires-Dist: nbformat>=5.0.0; extra == "notebooks"
Dynamic: license-file
